museum_security/__init__.py
museum_security-0.3.dist-info/METADATA
museum_security-0.3.dist-info/WHEEL
museum_security-0.3.dist-info/top_level.txt
museum_security-0.3.dist-info/RECORD
